README.md
setup.py
bmp_cred_credit_common/__init__.py
bmp_cred_credit_common.egg-info/PKG-INFO
bmp_cred_credit_common.egg-info/SOURCES.txt
bmp_cred_credit_common.egg-info/dependency_links.txt
bmp_cred_credit_common.egg-info/requires.txt
bmp_cred_credit_common.egg-info/top_level.txt