Metadata-Version: 2.1
Name: bmp-cred-credit-common
Version: 1.0.0
Summary: Qualquer problema é culpa do estagiário.
Author: O estagiário
Author-email: estagiario@bmp.com.br
